odoo/addons/event_type_multi_company/README.rst
odoo/addons/event_type_multi_company/__init__.py
odoo/addons/event_type_multi_company/__manifest__.py
odoo/addons/event_type_multi_company/i18n/event_type_multi_company.pot
odoo/addons/event_type_multi_company/i18n/it.po
odoo/addons/event_type_multi_company/models/__init__.py
odoo/addons/event_type_multi_company/models/event_event.py
odoo/addons/event_type_multi_company/models/event_type.py
odoo/addons/event_type_multi_company/readme/CONTRIBUTORS.rst
odoo/addons/event_type_multi_company/readme/DESCRIPTION.rst
odoo/addons/event_type_multi_company/security/security.xml
odoo/addons/event_type_multi_company/static/description/icon.png
odoo/addons/event_type_multi_company/static/description/index.html
odoo/addons/event_type_multi_company/views/event_type.xml
odoo13_addon_event_type_multi_company-13.0.1.0.1.dev6.dist-info/METADATA
odoo13_addon_event_type_multi_company-13.0.1.0.1.dev6.dist-info/WHEEL
odoo13_addon_event_type_multi_company-13.0.1.0.1.dev6.dist-info/top_level.txt
odoo13_addon_event_type_multi_company-13.0.1.0.1.dev6.dist-info/RECORD
